{"version": "1.0.0", "flags": {}, "imageHeight": 720, "imageWidth": 1280, "shapes": [{"label": "Red", "points": [[392.625, 336.125], [392.625, 353.875], [401.5, 336.125], [401.5, 353.875]], "group_id": 0, "shape_type": "polygon"}, {"label": "Red", "points": [[725.25, 282.75], [725.25, 300.125], [732.25, 282.75], [732.25, 300.125]], "group_id": 1, "shape_type": "polygon"}, {"label": "Green", "points": [[922.125, 282.5], [922.125, 314.75], [937.0, 282.5], [937.0, 314.75]], "group_id": 2, "shape_type": "polygon"}, {"label": "Red", "points": [[595.25, 332.5], [595.25, 354.875], [605.25, 332.5], [605.25, 354.875]], "group_id": 3, "shape_type": "polygon"}, {"label": "off", "points": [[530.25, 237.125], [530.25, 266.75], [544.875, 237.125], [544.875, 266.75]], "group_id": 4, "shape_type": "polygon"}], "imagePath": "218702.png"}