{"version": "1.0.0", "flags": {}, "imageHeight": 720, "imageWidth": 1280, "shapes": [{"label": "Red", "points": [[581.625, 309.375], [581.625, 319.0], [584.875, 309.375], [584.875, 319.0]], "group_id": 0, "shape_type": "polygon"}, {"label": "Green", "points": [[624.75, 307.5], [624.75, 317.0], [628.375, 307.5], [628.375, 317.0]], "group_id": 1, "shape_type": "polygon"}, {"label": "Green", "points": [[656.125, 310.375], [656.125, 320.375], [660.0, 310.375], [660.0, 320.375]], "group_id": 2, "shape_type": "polygon"}, {"label": "Green", "points": [[725.875, 334.875], [725.875, 344.125], [729.75, 334.875], [729.75, 344.125]], "group_id": 3, "shape_type": "polygon"}], "imagePath": "219080.png"}