{"version": "1.0.0", "flags": {}, "imageHeight": 720, "imageWidth": 1280, "shapes": [{"label": "Green", "points": [[699.0, 340.625], [699.0, 349.375], [702.0, 340.625], [702.0, 349.375]], "group_id": 0, "shape_type": "polygon"}, {"label": "Green", "points": [[637.25, 319.875], [637.25, 330.25], [641.0, 319.875], [641.0, 330.25]], "group_id": 1, "shape_type": "polygon"}, {"label": "Green", "points": [[721.5, 337.5], [721.5, 346.125], [724.125, 337.5], [724.125, 346.125]], "group_id": 2, "shape_type": "polygon"}], "imagePath": "229372.png"}